LICENSE
MANIFEST.in
README.md
requirements.txt
setup.py
djangocms_workflows.egg-info/PKG-INFO
djangocms_workflows.egg-info/SOURCES.txt
djangocms_workflows.egg-info/dependency_links.txt
djangocms_workflows.egg-info/requires.txt
djangocms_workflows.egg-info/top_level.txt
workflows/__init__.py
workflows/admin.py
workflows/apps.py
workflows/cms_toolbars.py
workflows/email.py
workflows/forms.py
workflows/models.py
workflows/tests.py
workflows/views.py
workflows/migrations/0001_initial.py
workflows/migrations/__init__.py
workflows/signals/__init__.py
workflows/signals/handlers.py
workflows/static/workflows/css/action_admin.css
workflows/static/workflows/css/sortable_inline.css
workflows/templates/workflows/admin/action_change_form.html
workflows/templates/workflows/admin/action_change_list.html
workflows/templates/workflows/admin/action_confirm.html
workflows/templates/workflows/admin/action_diff.html
workflows/templates/workflows/admin/action_form.html
workflows/templates/workflows/admin/close_sideframe_link.html