Metadata-Version: 1.1
Name: djangocms-workflows
Version: 0.2a1
Summary: Workflow system for Django-CMS.
Home-page: https://github.com/karalics/djangocms-workflows.git
Author: karalics
Author-email: slavisa.karalic@gmail.com
License: MIT License
